opik_optimizer/__init__.py
opik_optimizer/_llm_calls.py
opik_optimizer/_throttle.py
opik_optimizer/base_optimizer.py
opik_optimizer/helpers.py
opik_optimizer/logging_config.py
opik_optimizer/optimizable_agent.py
opik_optimizer/optimization_result.py
opik_optimizer/py.typed
opik_optimizer/reporting_utils.py
opik_optimizer/task_evaluator.py
opik_optimizer/algorithms/__init__.py
opik_optimizer/algorithms/evolutionary_optimizer/__init__.py
opik_optimizer/algorithms/evolutionary_optimizer/evolutionary_optimizer.py
opik_optimizer/algorithms/evolutionary_optimizer/helpers.py
opik_optimizer/algorithms/evolutionary_optimizer/mcp.py
opik_optimizer/algorithms/evolutionary_optimizer/prompts.py
opik_optimizer/algorithms/evolutionary_optimizer/reporting.py
opik_optimizer/algorithms/evolutionary_optimizer/ops/crossover_ops.py
opik_optimizer/algorithms/evolutionary_optimizer/ops/evaluation_ops.py
opik_optimizer/algorithms/evolutionary_optimizer/ops/mutation_ops.py
opik_optimizer/algorithms/evolutionary_optimizer/ops/population_ops.py
opik_optimizer/algorithms/evolutionary_optimizer/ops/style_ops.py
opik_optimizer/algorithms/few_shot_bayesian_optimizer/__init__.py
opik_optimizer/algorithms/few_shot_bayesian_optimizer/columnar_search_space.py
opik_optimizer/algorithms/few_shot_bayesian_optimizer/few_shot_bayesian_optimizer.py
opik_optimizer/algorithms/few_shot_bayesian_optimizer/prompts.py
opik_optimizer/algorithms/few_shot_bayesian_optimizer/reporting.py
opik_optimizer/algorithms/gepa_optimizer/__init__.py
opik_optimizer/algorithms/gepa_optimizer/adapter.py
opik_optimizer/algorithms/gepa_optimizer/gepa_optimizer.py
opik_optimizer/algorithms/gepa_optimizer/reporting.py
opik_optimizer/algorithms/hierarchical_reflective_optimizer/__init__.py
opik_optimizer/algorithms/hierarchical_reflective_optimizer/hierarchical_reflective_optimizer.py
opik_optimizer/algorithms/hierarchical_reflective_optimizer/hierarchical_root_cause_analyzer.py
opik_optimizer-2.3.11.dist-info/licenses/LICENSE
opik_optimizer-2.3.11.dist-info/METADATA
opik_optimizer-2.3.11.dist-info/WHEEL
opik_optimizer-2.3.11.dist-info/top_level.txt
opik_optimizer-2.3.11.dist-info/RECORD
