Metadata-Version: 2.4
Name: opik_optimizer
Version: 2.3.11
Summary: Agent optimization with Opik
Home-page: https://github.com/comet-ml/opik
Author: Comet ML
Author-email: Comet ML <support@comet.com>
License: Apache 2.0
Project-URL: Homepage, https://github.com/comet-ml/opik/blob/main/sdks/opik_optimizer/README.md
Project-URL: Repository, https://github.com/comet-ml/opik
Requires-Python: >=3.10,<3.14
License-File: LICENSE
Requires-Dist: datasets
Requires-Dist: deap>=1.4.3
Requires-Dist: gepa>=0.0.7
Requires-Dist: hf_xet
Requires-Dist: litellm!=1.75.0,!=1.75.1,!=1.75.2,!=1.75.3,!=1.75.4,!=1.75.5,!=1.77.3,!=1.77.4,!=1.77.5,!=1.77.7,!=1.78.0,!=1.78.2,!=1.78.3,!=1.78.4,!=1.78.5,!=1.78.6,!=1.78.7,!=1.79.0,!=1.79.1,>=1.79.2
Requires-Dist: mcp>=1.0.0
Requires-Dist: opik>=1.9.7
Requires-Dist: optuna
Requires-Dist: pandas
Requires-Dist: pydantic
Requires-Dist: pyrate-limiter
Requires-Dist: tqdm
Requires-Dist: rich
Requires-Dist: pillow
Provides-Extra: dev
Requires-Dist: pytest; extra == "dev"
Requires-Dist: pytest-cov; extra == "dev"
Requires-Dist: pytest-xdist; extra == "dev"
Requires-Dist: pytest-asyncio; extra == "dev"
Requires-Dist: pytest-env; extra == "dev"
Requires-Dist: pytest-profiling; extra == "dev"
Requires-Dist: langgraph; extra == "dev"
Requires-Dist: pre-commit; extra == "dev"
Requires-Dist: scikit-learn; extra == "dev"
Dynamic: author
Dynamic: home-page
Dynamic: license-file
Dynamic: requires-python
